Metadata-Version: 2.1
Name: Orange3-BPK-CAATT
Version: 1.1.1
Summary: Orange3 Computer Assisted Audit Technique Tools (CAATT) add-on.
Home-page: https://www.bpk.go.id/
Author: The Audit Board of The Republic of Indonesia (BPK-RI)
Author-email: eppid@bpk.go.id
Keywords: orange3-caatt,caatt,bpk-caatt
